abdallaabdelrhman/__init__.py
0x2nac0nda-0.1.dist-info/LICENSE.txt
0x2nac0nda-0.1.dist-info/METADATA
0x2nac0nda-0.1.dist-info/WHEEL
0x2nac0nda-0.1.dist-info/top_level.txt
0x2nac0nda-0.1.dist-info/RECORD
