Metadata-Version: 2.1
Name: 0x2nac0nda
Version: 0.1
Summary: This is a very simple script using Google Api into Searching, to get knowledge graph from Google
Author: Abdalla Abdelrhman
Author-email: anacondafortext@gmail.com
License: UNKNOWN
Platform: UNKNOWN
Classifier: Programming Language :: Python :: 3
Classifier: License :: OSI Approved :: MIT License
Classifier: Operating System :: OS Independent
License-File: LICENSE.txt
